booking/__init__.py
booking/admin.py
booking/apps.py
booking/models.py
booking/tests.py
booking/views.py
booking/migrations/0001_initial.py
booking/migrations/__init__.py
cheap_local_websites_booking-0.0.1.dist-info/LICENSE
cheap_local_websites_booking-0.0.1.dist-info/METADATA
cheap_local_websites_booking-0.0.1.dist-info/WHEEL
cheap_local_websites_booking-0.0.1.dist-info/top_level.txt
cheap_local_websites_booking-0.0.1.dist-info/RECORD
